cm_jupyter_eg_kernel_wlm/__init__.py
cm_jupyter_eg_kernel_wlm/_version.py
cm_jupyter_eg_kernel_wlm/ipykernel_wlm.py
cm_jupyter_eg_kernel_wlm/jupyter_kernel_starter/__init__.py
cm_jupyter_eg_kernel_wlm/jupyter_kernel_starter/cli.py
cm_jupyter_eg_kernel_wlm/jupyter_kernel_starter/conn_file.py
cm_jupyter_eg_kernel_wlm/jupyter_kernel_starter/consts.py
cm_jupyter_eg_kernel_wlm/jupyter_kernel_starter/encryptor.py
cm_jupyter_eg_kernel_wlm/jupyter_kernel_starter/handler.py
cm_jupyter_eg_kernel_wlm/jupyter_kernel_starter/ip_tools.py
cm_jupyter_eg_kernel_wlm/jupyter_kernel_starter/process_starter.py
cm_jupyter_eg_kernel_wlm-4.0.1.dist-info/METADATA
cm_jupyter_eg_kernel_wlm-4.0.1.dist-info/WHEEL
cm_jupyter_eg_kernel_wlm-4.0.1.dist-info/entry_points.txt
cm_jupyter_eg_kernel_wlm-4.0.1.dist-info/top_level.txt
cm_jupyter_eg_kernel_wlm-4.0.1.dist-info/RECORD
