Metadata-Version: 2.1
Name: cm-jupyter-eg-kernel-wlm
Version: 4.0.1
Summary: cm-jupyter-eg-kernel-wlm
Requires-Python: >=3.7
Requires-Dist: ipykernel >=5.1
Requires-Dist: bash-kernel >=0.7
Requires-Dist: pycryptodome >=3.15
Requires-Dist: cryptography >=42
Requires-Dist: psutil
